Workbook

Sheet About
A1: Retail Pharmacy - Sales Pattern Analytics (data-free edition)
A3: What this is | B3: The original analysis workbook with all transaction-level data removed. All 9 charts and all result tables are unchanged.
A4: Removed | B4: Raw Data (invoice lines, customer names, mobile numbers, batch numbers), Invoice Pivot, Basket Incidence, and the per-customer RFM table.
A5: Kept | B5: Segment, product, monthly and daily-demand aggregates; every chart; formulas that depend only on kept cells.
A6: Values vs formulas | B6: Cells that originally read from the removed sheets now hold their computed values. Downstream formulas (cumulative %, ABC/XYZ class, support/confidence/lift, trend fit, MAPE, safety stock, reorder point) are still live.
A7: Source data | B7: Six months of a Bengaluru retail pharmacy's billing data (1 Jan - 30 Jun 2024), used under written authorisation for academic purposes.

Sheet RFM Analysis
A1: Recency (days since last invoice, snapshot 2024-07-01), Frequency (unique invoices), and Monetary (total spend) computed live from 'Invoice Pivot'. R/M scores use quartile thresholds (QUARTILE); F score uses a tie-broken frequency rank (RANK + COUNTIF) before quartiling, matching the tie-handling used in the analysis. Segment = sum of R+F+M scores. [Data-free edition: the source data sheets were removed; cells that read from them hold the computed values.]
L2: Segment | M2: Customers | N2: % of Customers | O2: Avg. Recency | P2: Avg. Frequency | Q2: Avg. Monetary (₹) | R2: Revenue Share
A3: Per-customer RFM table (820 customers: IDs, R/F/M scores) removed from this public copy. Segment summary at right (columns L-R) is unchanged. | L3: High-Value Loyal | M3: 213 | N3: 0.2597561 | O3: 6.0798122 | P3: 21.586854 | Q3: 17636.977 | R3: 0.40854363
L4: Steady/Regular | M4: 309 | N4: 0.37682927 | O4: 9.8964401 | P4: 16.485437 | Q4: 10965.652 | R4: 0.36849163
L5: Occasional | M5: 194 | N5: 0.23658537 | O5: 14.963918 | P5: 12.994845 | Q5: 7577.1847 | R5: 0.15986165
L6: At-Risk/Infrequent | M6: 104 | N6: 0.12682927 | O6: 25 | P6: 10.980769 | Q6: 5579.3371 | R6: 0.06310309

Sheet ABC Analysis
A1: Revenue per product computed live via SUMIF on 'Raw Data'. Products are listed in descending revenue order (determined once from the source data); cumulative % and ABC class recalculate live from the Revenue column. Class A = cumulative revenue up to 70%, B = 70-90%, C = 90-100%. [Data-free edition: the source data sheets were removed; cells that read from them hold the computed values.]
A2: Product_Name | B2: Revenue (₹) | C2: Cumulative Revenue (₹) | D2: Cumulative % | E2: ABC_Class | G2: Class | H2: Products | I2: % of Products | J2: Revenue (₹) | K2: % of Revenue
A3: Insulin Glargine | B3: 2351440 | C3: =SUM($B$3:B3) | D3: =C3/SUM($B$3:$B$42) | E3: =IF(D3<=0.7,"A",IF(D3<=0.9,"B","C")) | G3: A | H3: =COUNTIF($E$3:$E$42,G3) | I3: =H3/COUNTA($A$3:$A$42) | J3: =SUMIF($E$3:$E$42,G3,$B$3:$B$42) | K3: =J3/SUM($B$3:$B$42)
A4: Salbutamol Inhaler | B4: 590009.28 | C4: =SUM($B$3:B4) | D4: =C4/SUM($B$3:$B$42) | E4: =IF(D4<=0.7,"A",IF(D4<=0.9,"B","C")) | G4: B | H4: =COUNTIF($E$3:$E$42,G4) | I4: =H4/COUNTA($A$3:$A$42) | J4: =SUMIF($E$3:$E$42,G4,$B$3:$B$42) | K4: =J4/SUM($B$3:$B$42)
A5: Atorvastatin 10mg | B5: 497183.4 | C5: =SUM($B$3:B5) | D5: =C5/SUM($B$3:$B$42) | E5: =IF(D5<=0.7,"A",IF(D5<=0.9,"B","C")) | G5: C | H5: =COUNTIF($E$3:$E$42,G5) | I5: =H5/COUNTA($A$3:$A$42) | J5: =SUMIF($E$3:$E$42,G5,$B$3:$B$42) | K5: =J5/SUM($B$3:$B$42)
A6: Vitamin D3 60K | B6: 421835.84 | C6: =SUM($B$3:B6) | D6: =C6/SUM($B$3:$B$42) | E6: =IF(D6<=0.7,"A",IF(D6<=0.9,"B","C"))
A7: Volini Spray 100g | B7: 284619.99 | C7: =SUM($B$3:B7) | D7: =C7/SUM($B$3:$B$42) | E7: =IF(D7<=0.7,"A",IF(D7<=0.9,"B","C"))
A8: Glimepiride 2mg | B8: 276560.2 | C8: =SUM($B$3:B8) | D8: =C8/SUM($B$3:$B$42) | E8: =IF(D8<=0.7,"A",IF(D8<=0.9,"B","C"))
A9: Amlodipine 5mg | B9: 262251.36 | C9: =SUM($B$3:B9) | D9: =C9/SUM($B$3:$B$42) | E9: =IF(D9<=0.7,"A",IF(D9<=0.9,"B","C"))
A10: Calcium + D3 | B10: 262144.08 | C10: =SUM($B$3:B10) | D10: =C10/SUM($B$3:$B$42) | E10: =IF(D10<=0.7,"A",IF(D10<=0.9,"B","C"))
A11: Levothyroxine 50mcg | B11: 257690.16 | C11: =SUM($B$3:B11) | D11: =C11/SUM($B$3:$B$42) | E11: =IF(D11<=0.7,"A",IF(D11<=0.9,"B","C"))
A12: Montelukast 10mg | B12: 235000.92 | C12: =SUM($B$3:B12) | D12: =C12/SUM($B$3:$B$42) | E12: =IF(D12<=0.7,"A",IF(D12<=0.9,"B","C"))
A13: Metoprolol 50mg | B13: 224967.12 | C13: =SUM($B$3:B13) | D13: =C13/SUM($B$3:$B$42) | E13: =IF(D13<=0.7,"A",IF(D13<=0.9,"B","C"))
A14: Vitamin C 500mg | B14: 195151.35 | C14: =SUM($B$3:B14) | D14: =C14/SUM($B$3:$B$42) | E14: =IF(D14<=0.7,"A",IF(D14<=0.9,"B","C"))
A15: Metformin 500mg | B15: 190699.6 | C15: =SUM($B$3:B15) | D15: =C15/SUM($B$3:$B$42) | E15: =IF(D15<=0.7,"A",IF(D15<=0.9,"B","C"))
A16: Moxifloxacin Eye Drops | B16: 188440.84 | C16: =SUM($B$3:B16) | D16: =C16/SUM($B$3:$B$42) | E16: =IF(D16<=0.7,"A",IF(D16<=0.9,"B","C"))
A17: Clonazepam 0.5mg | B17: 185312.4 | C17: =SUM($B$3:B17) | D17: =C17/SUM($B$3:$B$42) | E17: =IF(D17<=0.7,"A",IF(D17<=0.9,"B","C"))
... A42: ORS Sachet | B42: 20039.88 | C42: =SUM($B$3:B42) | D42: =C42/SUM($B$3:$B$42) | E42: =IF(D42<=0.7,"A",IF(D42<=0.9,"B","C"))

Sheet ABC-XYZ Analysis
A1: Monthly unit demand per product computed live via SUMIFS on 'Raw Data' (date range per calendar month). CV% = sample standard deviation / mean across the six months. XYZ class: X (CV<=20%) stable, Y (20-40%) moderately variable, Z (>40%) highly variable. ABC_Class is looked up from the 'ABC Analysis' sheet. [Data-free edition: the source data sheets were removed; cells that read from them hold the computed values.]
A2: Product_Name | B2: Jan-24 | C2: Feb-24 | D2: Mar-24 | E2: Apr-24 | F2: May-24 | G2: Jun-24 | H2: Mean | I2: StdDev (sample) | J2: CV % | K2: XYZ_Class | L2: ABC_Class | M2: ABC_XYZ | N2: Revenue (₹) | P2: ABC_XYZ | Q2: Products | R2: Revenue (₹) | S2: Revenue Share
A3: Insulin Glargine | B3: 453 | C3: 426 | D3: 449 | E3: 405 | F3: 378 | G3: 452 | H3: =AVERAGE(B3:G3) | I3: =STDEV(B3:G3) | J3: =I3/H3*100 | K3: =IF(J3<=20,"X",IF(J3<=40,"Y","Z")) | L3: =INDEX('ABC Analysis'!$E$3:$E$42,MATCH(A3,'ABC Analysis'!$A$3:$A$42,0)) | M3: =L3&K3 | N3: =INDEX('ABC Analysis'!$B$3:$B$42,MATCH(A3,'ABC Analysis'!$A$3:$A$42,0)) | P3: AX | Q3: =COUNTIF($M$3:$M$42,P3) | R3: =SUMIF($M$3:$M$42,P3,$N$3:$N$42) | S3: =R3/SUM($N$3:$N$42)
A4: Salbutamol Inhaler | B4: 344 | C4: 301 | D4: 229 | E4: 131 | F4: 178 | G4: 254 | H4: =AVERAGE(B4:G4) | I4: =STDEV(B4:G4) | J4: =I4/H4*100 | K4: =IF(J4<=20,"X",IF(J4<=40,"Y","Z")) | L4: =INDEX('ABC Analysis'!$E$3:$E$42,MATCH(A4,'ABC Analysis'!$A$3:$A$42,0)) | M4: =L4&K4 | N4: =INDEX('ABC Analysis'!$B$3:$B$42,MATCH(A4,'ABC Analysis'!$A$3:$A$42,0)) | P4: AY | Q4: =COUNTIF($M$3:$M$42,P4) | R4: =SUMIF($M$3:$M$42,P4,$N$3:$N$42) | S4: =R4/SUM($N$3:$N$42)
A5: Atorvastatin 10mg | B5: 413 | C5: 469 | D5: 452 | E5: 425 | F5: 439 | G5: 419 | H5: =AVERAGE(B5:G5) | I5: =STDEV(B5:G5) | J5: =I5/H5*100 | K5: =IF(J5<=20,"X",IF(J5<=40,"Y","Z")) | L5: =INDEX('ABC Analysis'!$E$3:$E$42,MATCH(A5,'ABC Analysis'!$A$3:$A$42,0)) | M5: =L5&K5 | N5: =INDEX('ABC Analysis'!$B$3:$B$42,MATCH(A5,'ABC Analysis'!$A$3:$A$42,0)) | P5: AZ | Q5: =COUNTIF($M$3:$M$42,P5) | R5: =SUMIF($M$3:$M$42,P5,$N$3:$N$42) | S5: =R5/SUM($N$3:$N$42)
A6: Vitamin D3 60K | B6: 164 | C6: 164 | D6: 215 | E6: 248 | F6: 223 | G6: 144 | H6: =AVERAGE(B6:G6) | I6: =STDEV(B6:G6) | J6: =I6/H6*100 | K6: =IF(J6<=20,"X",IF(J6<=40,"Y","Z")) | L6: =INDEX('ABC Analysis'!$E$3:$E$42,MATCH(A6,'ABC Analysis'!$A$3:$A$42,0)) | M6: =L6&K6 | N6: =INDEX('ABC Analysis'!$B$3:$B$42,MATCH(A6,'ABC Analysis'!$A$3:$A$42,0)) | P6: BX | Q6: =COUNTIF($M$3:$M$42,P6) | R6: =SUMIF($M$3:$M$42,P6,$N$3:$N$42) | S6: =R6/SUM($N$3:$N$42)
A7: Volini Spray 100g | B7: 243 | C7: 171 | D7: 193 | E7: 184 | F7: 245 | G7: 312 | H7: =AVERAGE(B7:G7) | I7: =STDEV(B7:G7) | J7: =I7/H7*100 | K7: =IF(J7<=20,"X",IF(J7<=40,"Y","Z")) | L7: =INDEX('ABC Analysis'!$E$3:$E$42,MATCH(A7,'ABC Analysis'!$A$3:$A$42,0)) | M7: =L7&K7 | N7: =INDEX('ABC Analysis'!$B$3:$B$42,MATCH(A7,'ABC Analysis'!$A$3:$A$42,0)) | P7: BY | Q7: =COUNTIF($M$3:$M$42,P7) | R7: =SUMIF($M$3:$M$42,P7,$N$3:$N$42) | S7: =R7/SUM($N$3:$N$42)
A8: Glimepiride 2mg | B8: 438 | C8: 389 | D8: 570 | E8: 415 | F8: 438 | G8: 449 | H8: =AVERAGE(B8:G8) | I8: =STDEV(B8:G8) | J8: =I8/H8*100 | K8: =IF(J8<=20,"X",IF(J8<=40,"Y","Z")) | L8: =INDEX('ABC Analysis'!$E$3:$E$42,MATCH(A8,'ABC Analysis'!$A$3:$A$42,0)) | M8: =L8&K8 | N8: =INDEX('ABC Analysis'!$B$3:$B$42,MATCH(A8,'ABC Analysis'!$A$3:$A$42,0)) | P8: BZ | Q8: =COUNTIF($M$3:$M$42,P8) | R8: =SUMIF($M$3:$M$42,P8,$N$3:$N$42) | S8: =R8/SUM($N$3:$N$42)
A9: Amlodipine 5mg | B9: 431 | C9: 476 | D9: 477 | E9: 468 | F9: 500 | G9: 345 | H9: =AVERAGE(B9:G9) | I9: =STDEV(B9:G9) | J9: =I9/H9*100 | K9: =IF(J9<=20,"X",IF(J9<=40,"Y","Z")) | L9: =INDEX('ABC Analysis'!$E$3:$E$42,MATCH(A9,'ABC Analysis'!$A$3:$A$42,0)) | M9: =L9&K9 | N9: =INDEX('ABC Analysis'!$B$3:$B$42,MATCH(A9,'ABC Analysis'!$A$3:$A$42,0)) | P9: CX | Q9: =COUNTIF($M$3:$M$42,P9) | R9: =SUMIF($M$3:$M$42,P9,$N$3:$N$42) | S9: =R9/SUM($N$3:$N$42)
A10: Calcium + D3 | B10: 209 | C10: 180 | D10: 299 | E10: 220 | F10: 197 | G10: 173 | H10: =AVERAGE(B10:G10) | I10: =STDEV(B10:G10) | J10: =I10/H10*100 | K10: =IF(J10<=20,"X",IF(J10<=40,"Y","Z")) | L10: =INDEX('ABC Analysis'!$E$3:$E$42,MATCH(A10,'ABC Analysis'!$A$3:$A$42,0)) | M10: =L10&K10 | N10: =INDEX('ABC Analysis'!$B$3:$B$42,MATCH(A10,'ABC Analysis'!$A$3:$A$42,0)) | P10: CY | Q10: =COUNTIF($M$3:$M$42,P10) | R10: =SUMIF($M$3:$M$42,P10,$N$3:$N$42) | S10: =R10/SUM($N$3:$N$42)
A11: Levothyroxine 50mcg | B11: 389 | C11: 438 | D11: 484 | E11: 439 | F11: 394 | G11: 364 | H11: =AVERAGE(B11:G11) | I11: =STDEV(B11:G11) | J11: =I11/H11*100 | K11: =IF(J11<=20,"X",IF(J11<=40,"Y","Z")) | L11: =INDEX('ABC Analysis'!$E$3:$E$42,MATCH(A11,'ABC Analysis'!$A$3:$A$42,0)) | M11: =L11&K11 | N11: =INDEX('ABC Analysis'!$B$3:$B$42,MATCH(A11,'ABC Analysis'!$A$3:$A$42,0)) | P11: CZ | Q11: =COUNTIF($M$3:$M$42,P11) | R11: =SUMIF($M$3:$M$42,P11,$N$3:$N$42) | S11: =R11/SUM($N$3:$N$42)
A12: Montelukast 10mg | B12: 224 | C12: 246 | D12: 187 | E12: 133 | F12: 211 | G12: 309 | H12: =AVERAGE(B12:G12) | I12: =STDEV(B12:G12) | J12: =I12/H12*100 | K12: =IF(J12<=20,"X",IF(J12<=40,"Y","Z")) | L12: =INDEX('ABC Analysis'!$E$3:$E$42,MATCH(A12,'ABC Analysis'!$A$3:$A$42,0)) | M12: =L12&K12 | N12: =INDEX('ABC Analysis'!$B$3:$B$42,MATCH(A12,'ABC Analysis'!$A$3:$A$42,0))
A13: Metoprolol 50mg | B13: 392 | C13: 431 | D13: 424 | E13: 359 | F13: 448 | G13: 400 | H13: =AVERAGE(B13:G13) | I13: =STDEV(B13:G13) | J13: =I13/H13*100 | K13: =IF(J13<=20,"X",IF(J13<=40,"Y","Z")) | L13: =INDEX('ABC Analysis'!$E$3:$E$42,MATCH(A13,'ABC Analysis'!$A$3:$A$42,0)) | M13: =L13&K13 | N13: =INDEX('ABC Analysis'!$B$3:$B$42,MATCH(A13,'ABC Analysis'!$A$3:$A$42,0))
A14: Vitamin C 500mg | B14: 166 | C14: 183 | D14: 253 | E14: 165 | F14: 218 | G14: 160 | H14: =AVERAGE(B14:G14) | I14: =STDEV(B14:G14) | J14: =I14/H14*100 | K14: =IF(J14<=20,"X",IF(J14<=40,"Y","Z")) | L14: =INDEX('ABC Analysis'!$E$3:$E$42,MATCH(A14,'ABC Analysis'!$A$3:$A$42,0)) | M14: =L14&K14 | N14: =INDEX('ABC Analysis'!$B$3:$B$42,MATCH(A14,'ABC Analysis'!$A$3:$A$42,0))
A15: Metformin 500mg | B15: 517 | C15: 464 | D15: 440 | E15: 464 | F15: 450 | G15: 385 | H15: =AVERAGE(B15:G15) | I15: =STDEV(B15:G15) | J15: =I15/H15*100 | K15: =IF(J15<=20,"X",IF(J15<=40,"Y","Z")) | L15: =INDEX('ABC Analysis'!$E$3:$E$42,MATCH(A15,'ABC Analysis'!$A$3:$A$42,0)) | M15: =L15&K15 | N15: =INDEX('ABC Analysis'!$B$3:$B$42,MATCH(A15,'ABC Analysis'!$A$3:$A$42,0))
A16: Moxifloxacin Eye Drops | B16: 196 | C16: 152 | D16: 189 | E16: 204 | F16: 243 | G16: 219 | H16: =AVERAGE(B16:G16) | I16: =STDEV(B16:G16) | J16: =I16/H16*100 | K16: =IF(J16<=20,"X",IF(J16<=40,"Y","Z")) | L16: =INDEX('ABC Analysis'!$E$3:$E$42,MATCH(A16,'ABC Analysis'!$A$3:$A$42,0)) | M16: =L16&K16 | N16: =INDEX('ABC Analysis'!$B$3:$B$42,MATCH(A16,'ABC Analysis'!$A$3:$A$42,0))
A17: Clonazepam 0.5mg | B17: 400 | C17: 412 | D17: 468 | E17: 435 | F17: 496 | G17: 436 | H17: =AVERAGE(B17:G17) | I17: =STDEV(B17:G17) | J17: =I17/H17*100 | K17: =IF(J17<=20,"X",IF(J17<=40,"Y","Z")) | L17: =INDEX('ABC Analysis'!$E$3:$E$42,MATCH(A17,'ABC Analysis'!$A$3:$A$42,0)) | M17: =L17&K17 | N17: =INDEX('ABC Analysis'!$B$3:$B$42,MATCH(A17,'ABC Analysis'!$A$3:$A$42,0))
A18: Calamine Lotion | B18: 147 | C18: 123 | D18: 240 | E18: 243 | F18: 274 | G18: 241 | H18: =AVERAGE(B18:G18) | I18: =STDEV(B18:G18) | J18: =I18/H18*100 | K18: =IF(J18<=20,"X",IF(J18<=40,"Y","Z")) | L18: =INDEX('ABC Analysis'!$E$3:$E$42,MATCH(A18,'ABC Analysis'!$A$3:$A$42,0)) | M18: =L18&K18 | N18: =INDEX('ABC Analysis'!$B$3:$B$42,MATCH(A18,'ABC Analysis'!$A$3:$A$42,0))
A19: Azithromycin 250mg | B19: 236 | C19: 234 | D19: 186 | E19: 150 | F19: 261 | G19: 267 | H19: =AVERAGE(B19:G19) | I19: =STDEV(B19:G19) | J19: =I19/H19*100 | K19: =IF(J19<=20,"X",IF(J19<=40,"Y","Z")) | L19: =INDEX('ABC Analysis'!$E$3:$E$42,MATCH(A19,'ABC Analysis'!$A$3:$A$42,0)) | M19: =L19&K19 | N19: =INDEX('ABC Analysis'!$B$3:$B$42,MATCH(A19,'ABC Analysis'!$A$3:$A$42,0))
A20: Pantoprazole 40mg | B20: 173 | C20: 169 | D20: 207 | E20: 192 | F20: 233 | G20: 147 | H20: =AVERAGE(B20:G20) | I20: =STDEV(B20:G20) | J20: =I20/H20*100 | K20: =IF(J20<=20,"X",IF(J20<=40,"Y","Z")) | L20: =INDEX('ABC Analysis'!$E$3:$E$42,MATCH(A20,'ABC Analysis'!$A$3:$A$42,0)) | M20: =L20&K20 | N20: =INDEX('ABC Analysis'!$B$3:$B$42,MATCH(A20,'ABC Analysis'!$A$3:$A$42,0))
A21: Alprazolam 0.25mg | B21: 414 | C21: 426 | D21: 388 | E21: 437 | F21: 473 | G21: 462 | H21: =AVERAGE(B21:G21) | I21: =STDEV(B21:G21) | J21: =I21/H21*100 | K21: =IF(J21<=20,"X",IF(J21<=40,"Y","Z")) | L21: =INDEX('ABC Analysis'!$E$3:$E$42,MATCH(A21,'ABC Analysis'!$A$3:$A$42,0)) | M21: =L21&K21 | N21: =INDEX('ABC Analysis'!$B$3:$B$42,MATCH(A21,'ABC Analysis'!$A$3:$A$42,0))
A22: Iron + Folic Syrup | B22: 160 | C22: 198 | D22: 177 | E22: 215 | F22: 188 | G22: 211 | H22: =AVERAGE(B22:G22) | I22: =STDEV(B22:G22) | J22: =I22/H22*100 | K22: =IF(J22<=20,"X",IF(J22<=40,"Y","Z")) | L22: =INDEX('ABC Analysis'!$E$3:$E$42,MATCH(A22,'ABC Analysis'!$A$3:$A$42,0)) | M22: =L22&K22 | N22: =INDEX('ABC Analysis'!$B$3:$B$42,MATCH(A22,'ABC Analysis'!$A$3:$A$42,0))
A23: Betamethasone Cream | B23: 155 | C23: 104 | D23: 272 | E23: 285 | F23: 277 | G23: 224 | H23: =AVERAGE(B23:G23) | I23: =STDEV(B23:G23) | J23: =I23/H23*100 | K23: =IF(J23<=20,"X",IF(J23<=40,"Y","Z")) | L23: =INDEX('ABC Analysis'!$E$3:$E$42,MATCH(A23,'ABC Analysis'!$A$3:$A$42,0)) | M23: =L23&K23 | N23: =INDEX('ABC Analysis'!$B$3:$B$42,MATCH(A23,'ABC Analysis'!$A$3:$A$42,0))
... A42: ORS Sachet | B42: 259 | C42: 199 | D42: 149 | E42: 181 | F42: 202 | G42: 247 | H42: =AVERAGE(B42:G42) | I42: =STDEV(B42:G42) | J42: =I42/H42*100 | K42: =IF(J42<=20,"X",IF(J42<=40,"Y","Z")) | L42: =INDEX('ABC Analysis'!$E$3:$E$42,MATCH(A42,'ABC Analysis'!$A$3:$A$42,0)) | M42: =L42&K42 | N42: =INDEX('ABC Analysis'!$B$3:$B$42,MATCH(A42,'ABC Analysis'!$A$3:$A$42,0))

Sheet Market Basket Analysis
A1: Support/Confidence/Lift for the top association-rule pairs, computed live from 'Basket Incidence' (1/0 flags per invoice for each of the 8 key products, restricted to the 7,399 invoices with 2+ product lines — matching the Apriori analysis, which only mines multi-item invoices). Count_A/Count_B = multi-item invoices containing that product; Co-count = multi-item invoices containing both (SUMPRODUCT of the two incidence columns). Support = Co-count / total multi-item invoices; Confidence = Co-count / Count_A; Lift = Confidence / (Count_B / total multi-item invoices). [Data-free edition: the source data sheets were removed; cells that read from them hold the computed values.]
A2: Product A | B2: Product B | C2: Col_A | D2: Col_B | E2: Count_A | F2: Count_B | G2: Co-count | H2: Total Invoices | I2: Support | J2: Confidence | K2: Lift | M2: Pair
A3: Clonazepam 0.5mg | B3: Amlodipine 5mg | C3: 1 | D3: 2 | E3: 845 | F3: 831 | G3: 149 | H3: 7399 | I3: =G3/H3 | J3: =G3/E3 | K3: =J3/(F3/H3) | M3: =A3&" + "&B3
A4: Alprazolam 0.25mg | B4: Amlodipine 5mg | C4: 3 | D4: 2 | E4: 839 | F4: 831 | G4: 144 | H4: 7399 | I4: =G4/H4 | J4: =G4/E4 | K4: =J4/(F4/H4) | M4: =A4&" + "&B4
A5: Clonazepam 0.5mg | B5: Alprazolam 0.25mg | C5: 1 | D5: 3 | E5: 845 | F5: 839 | G5: 144 | H5: 7399 | I5: =G5/H5 | J5: =G5/E5 | K5: =J5/(F5/H5) | M5: =A5&" + "&B5
A6: Clonazepam 0.5mg | B6: Glimepiride 2mg | C6: 1 | D6: 4 | E6: 845 | F6: 840 | G6: 140 | H6: 7399 | I6: =G6/H6 | J6: =G6/E6 | K6: =J6/(F6/H6) | M6: =A6&" + "&B6
A7: Atorvastatin 10mg | B7: Metoprolol 50mg | C7: 5 | D7: 6 | E7: 840 | F7: 815 | G7: 134 | H7: 7399 | I7: =G7/H7 | J7: =G7/E7 | K7: =J7/(F7/H7) | M7: =A7&" + "&B7
A8: Levothyroxine 50mcg | B8: Atorvastatin 10mg | C8: 7 | D8: 5 | E8: 775 | F8: 840 | G8: 126 | H8: 7399 | I8: =G8/H8 | J8: =G8/E8 | K8: =J8/(F8/H8) | M8: =A8&" + "&B8
A9: Glimepiride 2mg | B9: Metformin 500mg | C9: 4 | D9: 8 | E9: 840 | F9: 832 | G9: 135 | H9: 7399 | I9: =G9/H9 | J9: =G9/E9 | K9: =J9/(F9/H9) | M9: =A9&" + "&B9
A10: Atorvastatin 10mg | B10: Glimepiride 2mg | C10: 5 | D10: 4 | E10: 840 | F10: 840 | G10: 135 | H10: 7399 | I10: =G10/H10 | J10: =G10/E10 | K10: =J10/(F10/H10) | M10: =A10&" + "&B10

Sheet Demand Forecast
A1: Monthly revenue computed live via SUMIFS on 'Raw Data'. Holdout validation trains a linear trend (SLOPE/INTERCEPT) on Jan-May and tests it against actual June to compute MAE and MAPE. The full-data trend (all 6 months) is then used to project July 2024. [Data-free edition: the source data sheets were removed; cells that read from them hold the computed values.]
A2: Month | B2: Month Index | C2: Revenue (₹) | D2: Trend Fit (trained Jan-May)
A3: Jan-24 | B3: 1 | C3: 1543743.5 | D3: =$B$11*B3+$B$12
A4: Feb-24 | B4: 2 | C4: 1475679.7 | D4: =$B$11*B4+$B$12
A5: Mar-24 | B5: 3 | C5: 1611921.7 | D5: =$B$11*B5+$B$12
A6: Apr-24 | B6: 4 | C6: 1469148.8 | D6: =$B$11*B6+$B$12
A7: May-24 | B7: 5 | C7: 1524644.4 | D7: =$B$11*B7+$B$12
A8: Jun-24 | B8: 6 | C8: 1570149.3 | D8: =$B$11*B8+$B$12
A10: Holdout validation (trained on Jan-May, tested against actual June):
A11: Train Slope | B11: =SLOPE(C3:C7,B3:B7)
A12: Train Intercept | B12: =INTERCEPT(C3:C7,B3:B7)
A13: Predicted June Revenue | B13: =B11*B8+B12
A14: Actual June Revenue | B14: =C8
A15: MAE | B15: =ABS(B13-B14)
A16: MAPE | B16: =B15/B14
A18: Full-data trend (all 6 months) and July 2024 forecast:
A19: Full Slope | B19: =SLOPE(C3:C8,B3:B8)
A20: Full Intercept | B20: =INTERCEPT(C3:C8,B3:B8)
A21: July 2024 Forecast | B21: =B19*7+B20
A23: Chart data: monthly revenue with July 2024 forecast (Actual / Forecast split for two-colour bars)
A24: Month | B24: Actual Revenue (₹) | C24: Forecast Revenue (₹)
A25: Jan-24 | B25: =C3
A26: Feb-24 | B26: =C4
A27: Mar-24 | B27: =C5
A28: Apr-24 | B28: =C6
A29: May-24 | B29: =C7
A30: Jun-24 | B30: =C8
A31: Jul-24 (F) | C31: =B21

Sheet Safety Stock (AY Products)
A1: Safety stock and reorder point for the 5 AY (high-revenue, unstable-demand) products, using each product's daily-demand mean and sample standard deviation from 'Daily Demand Detail'. Assumptions (yellow): 3-day replenishment lead time; Z = 1.65 for a 95% service level. Safety Stock = Z x StdDev x SQRT(Lead Time). Reorder Point = (Avg. Daily Demand x Lead Time) + Safety Stock.
A2: Product | B2: Revenue (₹) | C2: Demand CV % | D2: Avg. Daily Demand (units) | E2: StdDev Daily Demand | F2: Lead Time (days) | G2: Safety Stock (units) | H2: Reorder Point (units) | J2: Assumptions:
A3: Salbutamol Inhaler | B3: =INDEX('ABC Analysis'!$B$3:$B$42,MATCH(A3,'ABC Analysis'!$A$3:$A$42,0)) | C3: =INDEX('ABC-XYZ Analysis'!$J$3:$J$42,MATCH(A3,'ABC-XYZ Analysis'!$A$3:$A$42,0)) | D3: =AVERAGE('Daily Demand Detail'!$B$3:$B$184) | E3: =STDEV('Daily Demand Detail'!$B$3:$B$184) | F3: =$K$3 | G3: =ROUND($K$4*E3*SQRT(F3),0) | H3: =ROUND(D3*F3+G3,0) | J3: Lead Time (days) | K3: 3
A4: Vitamin D3 60K | B4: =INDEX('ABC Analysis'!$B$3:$B$42,MATCH(A4,'ABC Analysis'!$A$3:$A$42,0)) | C4: =INDEX('ABC-XYZ Analysis'!$J$3:$J$42,MATCH(A4,'ABC-XYZ Analysis'!$A$3:$A$42,0)) | D4: =AVERAGE('Daily Demand Detail'!$C$3:$C$184) | E4: =STDEV('Daily Demand Detail'!$C$3:$C$184) | F4: =$K$3 | G4: =ROUND($K$4*E4*SQRT(F4),0) | H4: =ROUND(D4*F4+G4,0) | J4: Service Level Z | K4: 1.65
A5: Volini Spray 100g | B5: =INDEX('ABC Analysis'!$B$3:$B$42,MATCH(A5,'ABC Analysis'!$A$3:$A$42,0)) | C5: =INDEX('ABC-XYZ Analysis'!$J$3:$J$42,MATCH(A5,'ABC-XYZ Analysis'!$A$3:$A$42,0)) | D5: =AVERAGE('Daily Demand Detail'!$D$3:$D$184) | E5: =STDEV('Daily Demand Detail'!$D$3:$D$184) | F5: =$K$3 | G5: =ROUND($K$4*E5*SQRT(F5),0) | H5: =ROUND(D5*F5+G5,0)
A6: Montelukast 10mg | B6: =INDEX('ABC Analysis'!$B$3:$B$42,MATCH(A6,'ABC Analysis'!$A$3:$A$42,0)) | C6: =INDEX('ABC-XYZ Analysis'!$J$3:$J$42,MATCH(A6,'ABC-XYZ Analysis'!$A$3:$A$42,0)) | D6: =AVERAGE('Daily Demand Detail'!$E$3:$E$184) | E6: =STDEV('Daily Demand Detail'!$E$3:$E$184) | F6: =$K$3 | G6: =ROUND($K$4*E6*SQRT(F6),0) | H6: =ROUND(D6*F6+G6,0)
A7: Calcium + D3 | B7: =INDEX('ABC Analysis'!$B$3:$B$42,MATCH(A7,'ABC Analysis'!$A$3:$A$42,0)) | C7: =INDEX('ABC-XYZ Analysis'!$J$3:$J$42,MATCH(A7,'ABC-XYZ Analysis'!$A$3:$A$42,0)) | D7: =AVERAGE('Daily Demand Detail'!$F$3:$F$184) | E7: =STDEV('Daily Demand Detail'!$F$3:$F$184) | F7: =$K$3 | G7: =ROUND($K$4*E7*SQRT(F7),0) | H7: =ROUND(D7*F7+G7,0)

Sheet Descriptive Statistics
A1: Invoice-value and basket-size statistics computed live from 'Invoice Pivot' (one row per invoice, Invoice_Total and Item_Count columns). [Data-free edition: the source data sheets were removed; cells that read from them hold the computed values.]
A3: Invoice Value (₹)
A4: Count (invoices) | B4: 13355
A5: Mean | B5: 688.52771
A6: Median | B6: 395.08
A7: Standard Deviation | B7: 929.98511
A8: Minimum | B8: 14.28
A9: Maximum | B9: 10466.4
A10: Range | B10: =B9-B8
A11: 1st Quartile (Q1) | B11: 190.4
A12: 3rd Quartile (Q3) | B12: 836.84
A13: Coefficient of Variation | B13: =B7/B5*100
A16: Basket Size (items/invoice)
A17: Mean | B17: 1.9102958
A18: Median | B18: 2
A19: Mode | B19: 1
A20: Minimum | B20: 1
A21: Maximum | B21: 4
A22: Standard Deviation | B22: 0.99747075

Sheet Daily Demand Detail
A1: Daily unit demand for the five AY (high-revenue, variable-demand) products, computed live via SUMIFS on 'Raw Data'. Zero is entered on days with no recorded sale so the average and standard deviation reflect the full 182-day period (1 Jan-30 Jun 2024), not just days with a sale. [Data-free edition: the source data sheets were removed; cells that read from them hold the computed values.]
A2: Date | B2: Salbutamol Inhaler | C2: Vitamin D3 60K | D2: Volini Spray 100g | E2: Montelukast 10mg | F2: Calcium + D3
A3: 45292 | B3: 11 | C3: 8 | D3: 4 | E3: 5 | F3: 3
A4: 45293 | B4: 8 | C4: 2 | D4: 5 | E4: 9 | F4: 11
A5: 45294 | B5: 31 | C5: 2 | D5: 11 | E5: 18 | F5: 4
A6: 45295 | B6: 18 | C6: 0 | D6: 12 | E6: 7 | F6: 0
A7: 45296 | B7: 11 | C7: 6 | D7: 10 | E7: 14 | F7: 13
A8: 45297 | B8: 9 | C8: 4 | D8: 15 | E8: 8 | F8: 7
A9: 45298 | B9: 13 | C9: 0 | D9: 5 | E9: 5 | F9: 2
A10: 45299 | B10: 3 | C10: 4 | D10: 0 | E10: 9 | F10: 8
A11: 45300 | B11: 8 | C11: 0 | D11: 19 | E11: 4 | F11: 10
A12: 45301 | B12: 17 | C12: 0 | D12: 3 | E12: 5 | F12: 11
A13: 45302 | B13: 12 | C13: 13 | D13: 0 | E13: 4 | F13: 1
A14: 45303 | B14: 11 | C14: 5 | D14: 28 | E14: 5 | F14: 18
... A184: 45473 | B184: 1 | C184: 2 | D184: 7 | E184: 4 | F184: 11
